replenigo/__init__.py
replenigo/config.py
replenigo/definitions.py
replenigo/main.py
replenigo/replenigo.defaults.yaml
replenigo/session.py
replenigo/utils.py
replenigo-0.1.0.dist-info/entry_points.txt
replenigo-0.1.0.dist-info/METADATA
replenigo-0.1.0.dist-info/WHEEL
replenigo-0.1.0.dist-info/RECORD
