Metadata-Version: 2.1
Name: replenigo
Version: 0.1.0
Summary: Script that utilizes Sbanken's Open Banking API to refill accounts to specified balances
Home-page: https://github.com/mathiazom/replenigo
Author: Mathias Oterhals Myklebust
Author-email: mathias@oterbust.no
Requires-Python: >=3.10,<4.0
Classifier: Development Status :: 4 - Beta
Classifier: Intended Audience :: Developers
Classifier: License :: OSI Approved :: MIT License
Classifier: Operating System :: OS Independent
Classifier: Programming Language :: Python :: 3
Classifier: Programming Language :: Python :: 3.10
Classifier: Programming Language :: Python :: 3.11
Classifier: Programming Language :: Python :: 3.10
Requires-Dist: oauthlib (>=3.2.2,<4.0.0)
Requires-Dist: pyyaml (>=6.0,<7.0)
Requires-Dist: requests-oauthlib (>=1.3.1,<2.0.0)
Requires-Dist: rich (>=12.6.0,<13.0.0)
Requires-Dist: termcolor (>=2.1.1,<3.0.0)
Requires-Dist: typer[all] (>=0.3.0,<0.4.0)
Project-URL: Bug Tracker, https://github.com/mathiazom/replenigo/issues
Project-URL: Repository, https://github.com/mathiazom/replenigo
